LICENSE
MANIFEST.in
README.md
pyproject.toml
setup.cfg
setup.py
docassemble.KinshipConnector.egg-info/PKG-INFO
docassemble.KinshipConnector.egg-info/SOURCES.txt
docassemble.KinshipConnector.egg-info/dependency_links.txt
docassemble.KinshipConnector.egg-info/not-zip-safe
docassemble.KinshipConnector.egg-info/top_level.txt
docassemble/KinshipConnector/__init__.py
docassemble/KinshipConnector/data/questions/adoption-questions.yml
docassemble/KinshipConnector/data/questions/common_info.yml
docassemble/KinshipConnector/data/questions/generic-questions.yml
docassemble/KinshipConnector/data/questions/guardianship-questions.yml
docassemble/KinshipConnector/data/questions/kin.yml
docassemble/KinshipConnector/data/questions/temporary-care-agreement-questions.yml
docassemble/KinshipConnector/data/sources/README.md
docassemble/KinshipConnector/data/static/README.md
docassemble/KinshipConnector/data/static/adoption.png
docassemble/KinshipConnector/data/static/bootstrap.min.css
docassemble/KinshipConnector/data/static/circle-icon-court1x.svg
docassemble/KinshipConnector/data/static/circle-icon-doc1x.svg
docassemble/KinshipConnector/data/static/circle-icon-id1x.svg
docassemble/KinshipConnector/data/static/circle-icon-print1x.svg
docassemble/KinshipConnector/data/static/circle-icon-time1x.svg
docassemble/KinshipConnector/data/static/diy.png
docassemble/KinshipConnector/data/static/download.png
docassemble/KinshipConnector/data/static/guardianship.png
docassemble/KinshipConnector/data/static/guided-questions.png
docassemble/KinshipConnector/data/static/icon-bank1x.svg
docassemble/KinshipConnector/data/static/icon-clock.png
docassemble/KinshipConnector/data/static/icon-clock1x.svg
docassemble/KinshipConnector/data/static/icon-cost.png
docassemble/KinshipConnector/data/static/icon-info1x.svg
docassemble/KinshipConnector/data/static/icon-kinship-caregivers.png
docassemble/KinshipConnector/data/static/icon-time.png
docassemble/KinshipConnector/data/static/icon-west-virginia.png
docassemble/KinshipConnector/data/static/questionnaire.png
docassemble/KinshipConnector/data/static/step1.png
docassemble/KinshipConnector/data/static/step2-1.png
docassemble/KinshipConnector/data/static/step3-1.png
