Metadata-Version: 2.4
Name: docassemble.KinshipConnector
Version: 1.1.1
Summary: A docassemble extension to assist clients with educating themselves on the different types of kinship documents and create completed documents once chosen.
Home-page: https://docassemble.org
Author: Dane Henry, Esq.
Author-email: dhenry@lawv.net
License: The MIT License (MIT)
License-File: LICENSE
Dynamic: author
Dynamic: author-email
Dynamic: description
Dynamic: description-content-type
Dynamic: home-page
Dynamic: license
Dynamic: license-file
Dynamic: summary
